pyprimejs/__init__.py
pyprimejs-0.0.2.dist-info/LICENSE.txt
pyprimejs-0.0.2.dist-info/METADATA
pyprimejs-0.0.2.dist-info/WHEEL
pyprimejs-0.0.2.dist-info/top_level.txt
pyprimejs-0.0.2.dist-info/RECORD
