Metadata-Version: 2.1
Name: pyprimejs
Version: 0.0.2
Summary: A tool to find prime numbers
Home-page: UNKNOWN
Author: Jofre44
Author-email: jofre44@gmail.com
License: UNKNOWN
Platform: UNKNOWN
Classifier: Programming Language :: Python :: 3
Classifier: License :: OSI Approved :: MIT License
Classifier: Operating System :: OS Independent
Requires-Python: >=3.6
Requires-Dist: rpy2 (>=3.4.3)
